setup.py
pytestipdb/__init__.py
pytestipdb/ptipdb.py
robpol86_pytest_ipdb.egg-info/PKG-INFO
robpol86_pytest_ipdb.egg-info/SOURCES.txt
robpol86_pytest_ipdb.egg-info/dependency_links.txt
robpol86_pytest_ipdb.egg-info/entry_points.txt
robpol86_pytest_ipdb.egg-info/requires.txt
robpol86_pytest_ipdb.egg-info/top_level.txt