Metadata-Version: 1.1
Name: robpol86-pytest-ipdb
Version: 0.0.1
Summary: pytest-ipdb installable from pip. Using this until https://github.com/mverteuil/pytest-ipdb/issues/9 is resolved.
Home-page: https://github.com/mverteuil/pytest-ipdb
Author: Robpol86
Author-email: robpol86@gmail.com
License: UNKNOWN
Platform: UNKNOWN
Classifier: Development Status :: 2 - Pre-Alpha
Classifier: Environment :: Console
Classifier: Environment :: Plugins
Classifier: Intended Audience :: Developers
Classifier: License :: OSI Approved :: MIT License
Classifier: Operating System :: MacOS :: MacOS X
Classifier: Operating System :: POSIX
Classifier: Programming Language :: Python
Classifier: Topic :: Communications :: Email
Classifier: Topic :: Software Development :: Debuggers
Classifier: Topic :: Software Development :: Testing
